kafkaPythonWrapper/__init__.py
kafkaPythonWrapper/kafka_consumer.py
kafkaPythonWrapper/kafka_producer.py
kafkaPythonWrapper/logger.py
kafkaPythonWrapper-0.1.3.data/scripts/kafkaPython
kafkaPythonWrapper-0.1.3.dist-info/LICENSE
kafkaPythonWrapper-0.1.3.dist-info/METADATA
kafkaPythonWrapper-0.1.3.dist-info/WHEEL
kafkaPythonWrapper-0.1.3.dist-info/top_level.txt
kafkaPythonWrapper-0.1.3.dist-info/RECORD
