Metadata-Version: 2.1
Name: kafkaPythonWrapper
Version: 0.1.3
Summary: A wrapper for kafka-python
Home-page: https://github.com/Weizhang2017/pythonKakfaWrapper
Author: Wei Zhang
Author-email: zhangw1.2011@gmail.com
License: UNKNOWN
Platform: UNKNOWN
Classifier: Programming Language :: Python :: 3
Classifier: License :: OSI Approved :: MIT License
Classifier: Operating System :: OS Independent
Requires-Python: >=3.7
Requires-Dist: kafka-python
